tahoe_scorm/__init__.py
tahoe_scorm/exceptions.py
tahoe_scorm/storages.py
tahoe_scorm-0.2.0.dist-info/LICENSE
tahoe_scorm-0.2.0.dist-info/METADATA
tahoe_scorm-0.2.0.dist-info/WHEEL
tahoe_scorm-0.2.0.dist-info/top_level.txt
tahoe_scorm-0.2.0.dist-info/RECORD
