Metadata-Version: 2.1
Name: tahoe-scorm
Version: 0.2.0
Summary: Tahoe SCORM Customizations package.
License-File: LICENSE
